keras_ex/__init__.py
keras_ex/metrics/__init__.py
keras_ex/metrics/_classes.py
keras_ex/model_selection/__init__.py
keras_ex/model_selection/_plot.py
keras_ex-0.0.3.dist-info/LICENSE
keras_ex-0.0.3.dist-info/METADATA
keras_ex-0.0.3.dist-info/WHEEL
keras_ex-0.0.3.dist-info/top_level.txt
keras_ex-0.0.3.dist-info/RECORD
