Metadata-Version: 2.1
Name: keras-ex
Version: 0.0.3
Summary: self defined functions for keras
Home-page: https://github.com/aierwiki/keras-ex.git
Author: Tang Yubin
Author-email: tang-yu-bin@qq.com
License: UNKNOWN
Platform: UNKNOWN
Classifier: Programming Language :: Python :: 3
Classifier: License :: OSI Approved :: MIT License
Classifier: Operating System :: OS Independent
